LICENSE.txt
LICENSE.zip
MANIFEST.in
ProgramExecutableAnalyzer.py
README.md
setup.cfg
setup.py
ProgramExecutableAnalyzer.egg-info/PKG-INFO
ProgramExecutableAnalyzer.egg-info/SOURCES.txt
ProgramExecutableAnalyzer.egg-info/dependency_links.txt
ProgramExecutableAnalyzer.egg-info/top_level.txt