Metadata-Version: 2.1
Name: ProgramExecutableAnalyzer
Version: 0.0.4
Summary: This script analyzes MZ-PE (MS-DOS) executable.
Home-page: https://github.com/mauricelambert/ProgramExecutableAnalyzer
Author: Maurice Lambert
Author-email: mauricelambert434@gmail.com
Maintainer: Maurice Lambert
Maintainer-email: mauricelambert434@gmail.com
License: GPL-3.0 License
Project-URL: Executable, https://mauricelambert.github.io/info/python/security/ProgramExecutableAnalyzer.pyz
Keywords: PE,MZ,DLL,MS-DOS,Program,Forensic,Analysis,Executable,Malware-Analysis,Reverse-Engineering
Platform: Windows
Platform: Linux
Platform: MacOS
Classifier: Topic :: Security
Classifier: Environment :: Console
Classifier: Natural Language :: English
Classifier: Programming Language :: Python
Classifier: Programming Language :: Python :: 3.9
Classifier: Operating System :: MacOS
Classifier: Operating System :: POSIX :: Linux
Classifier: Operating System :: Microsoft :: Windows
Classifier: Development Status :: 5 - Production/Stable
Classifier: License :: OSI Approved :: GNU General Public License v3 (GPLv3)
Requires-Python: >=3.8
License-File: LICENSE.txt
License-File: LICENSE.zip
